mcp_server_testing/__init__.py
mcp_server_testing/__main__.py
mcp_server_testing/server.py
mcp_server_testing-0.2.0.dist-info/METADATA
mcp_server_testing-0.2.0.dist-info/WHEEL
mcp_server_testing-0.2.0.dist-info/entry_points.txt
mcp_server_testing-0.2.0.dist-info/RECORD
