Metadata-Version: 2.4
Name: mcp-server-testing
Version: 0.2.0
Summary: A test server implementation for Model Context Protocol (MCP)
Author-email: yareyaredesuyo <yareyaredesuyo@gmail.com>
License-Expression: MIT
Keywords: automation,llm,mcp,model-context-protocol
Classifier: Development Status :: 4 - Beta
Classifier: Intended Audience :: Developers
Classifier: License :: OSI Approved :: MIT License
Classifier: Programming Language :: Python :: 3
Classifier: Programming Language :: Python :: 3.10
Classifier: Topic :: Software Development :: Libraries :: Python Modules
Requires-Python: >=3.10
Requires-Dist: argparse>=1.4.0
Requires-Dist: fastmcp>=2.5.2
